Qsqlite/Qsqlite.py
Qsqlite/__init__.py
Qsqlite-0.974.dist-info/LICENSE
Qsqlite-0.974.dist-info/METADATA
Qsqlite-0.974.dist-info/WHEEL
Qsqlite-0.974.dist-info/entry_points.txt
Qsqlite-0.974.dist-info/top_level.txt
Qsqlite-0.974.dist-info/RECORD
