Metadata-Version: 2.1
Name: Qsqlite
Version: 0.974
Summary: Quick Sqlite Tools
Home-page: https://github.com/wolf71/Qsqlite
Author: Charles Lai
Author-email: 
Classifier: Programming Language :: Python :: 3
Classifier: License :: OSI Approved :: MIT License
Classifier: Operating System :: OS Independent
License-File: LICENSE
